{"2018-3":[{"title":"我的2016书单","date":"2018-03-29T11:35:37.000Z","link":"/阅读/我的2016书单/"},{"title":"我的2016电影","date":"2018-03-31T05:12:25.000Z","link":"/影音/我的2016电影/"},{"title":"C++字符串操作","date":"2018-03-31T08:55:28.000Z","link":"/语言/C++字符串操作/"}],"2018-4":[{"title":"我的2017书单","date":"2018-04-01T03:00:34.000Z","link":"/阅读/我的2017书单/"},{"title":"《控方证人》观后感","date":"2018-04-03T06:41:00.000Z","link":"/影音/《控方证人》观后感/"},{"title":"ZCMU-1620","date":"2018-04-10T13:11:41.000Z","link":"/题解集/ZCMU-1620/"},{"title":"ZCMU2034","date":"2018-04-11T07:30:33.000Z","link":"/题解集/ZCMU-2034/"},{"title":"区间贪心","date":"2018-04-11T09:44:16.000Z","link":"/算法和数据结构/区间贪心/"},{"title":"归并排序","date":"2018-04-11T10:23:35.000Z","link":"/算法和数据结构/归并排序/"},{"title":"好了歌","date":"2018-04-11T13:09:09.000Z","link":"/阅读/好了歌/"},{"title":"长恨歌","date":"2018-04-12T08:17:13.000Z","link":"/阅读/长恨歌/"},{"title":"洛神赋","date":"2018-04-13T06:27:03.000Z","link":"/阅读/洛神赋/"},{"title":"八大排序","date":"2018-04-13T07:38:10.000Z","link":"/算法和数据结构/八大排序/"},{"title":"My movie list of 2017","date":"2018-04-16T08:18:54.000Z","link":"/影音/My-movie-list-of-2017/"},{"title":"模式匹配","date":"2018-04-17T07:57:20.000Z","link":"/算法和数据结构/模式匹配/"},{"title":"大整数运算","date":"2018-04-18T11:10:41.000Z","link":"/算法和数据结构/大整数运算/"},{"title":"素数问题","date":"2018-04-18T11:12:48.000Z","link":"/算法和数据结构/素数问题/"},{"title":"algorithm头文件下常用函数","date":"2018-04-23T13:42:07.000Z","link":"/语言/algorithm头文件下常用函数/"},{"title":"组合数","date":"2018-04-24T06:34:22.000Z","link":"/算法和数据结构/组合数/"},{"title":"葬花词","date":"2018-04-29T04:50:41.000Z","link":"/阅读/葬花词/"},{"title":"《素媛》与《熔炉》","date":"2018-04-29T13:06:34.000Z","link":"/影音/《素媛》与《熔炉》/"},{"title":"二叉树的遍历","date":"2018-04-29T14:13:41.000Z","link":"/算法和数据结构/二叉树的遍历/"}],"2018-5":[{"title":"二叉查找树","date":"2018-05-01T13:38:15.000Z","link":"/算法和数据结构/二叉查找树/"},{"title":"平衡二叉树","date":"2018-05-02T11:14:55.000Z","link":"/算法和数据结构/平衡二叉树/"},{"title":"并查集","date":"2018-05-02T11:49:07.000Z","link":"/算法和数据结构/并查集/"},{"title":"堆的简介","date":"2018-05-03T11:53:51.000Z","link":"/算法和数据结构/堆的简介/"},{"title":"图的存储和遍历","date":"2018-05-04T09:10:20.000Z","link":"/算法和数据结构/图的存储和遍历/"},{"title":"最短路问题","date":"2018-05-09T11:45:53.000Z","link":"/算法和数据结构/最短路问题/"},{"title":"最小生成树","date":"2018-05-10T12:21:08.000Z","link":"/算法和数据结构/最小生成树/"},{"title":"拓扑排序","date":"2018-05-11T13:09:24.000Z","link":"/算法和数据结构/拓扑排序/"},{"title":"dp简介","date":"2018-05-12T08:43:12.000Z","link":"/算法和数据结构/dp简介/"},{"title":"最大连续子列和","date":"2018-05-13T03:57:35.000Z","link":"/算法和数据结构/最大连续子列和/"},{"title":"最长不下降子序列","date":"2018-05-14T07:25:42.000Z","link":"/算法和数据结构/最长不下降子序列/"},{"title":"最长公共子序列","date":"2018-05-14T07:47:17.000Z","link":"/算法和数据结构/最长公共子序列/"},{"title":"最长回文子串","date":"2018-05-15T06:40:37.000Z","link":"/算法和数据结构/最长回文子串/"},{"title":"LeetCode 5. 最长回文子串","date":"2018-05-15T08:23:42.000Z","link":"/题解集/LeetCode-5-最长回文子串/"},{"title":"01背包","date":"2018-05-16T11:45:01.000Z","link":"/算法和数据结构/01背包/"},{"title":"完全背包","date":"2018-05-16T11:45:25.000Z","link":"/算法和数据结构/完全背包/"},{"title":"LeetCode 1.两数之和","date":"2018-05-17T07:38:09.000Z","link":"/题解集/LeetCode-1-两数之和/"},{"title":"LeetCode 136.只出现一次的数字","date":"2018-05-17T07:46:22.000Z","link":"/题解集/LeetCode-136-只出现一次的数字/"},{"title":"LeetCode 167. 两数之和 II - 输入有序数组","date":"2018-05-17T07:49:13.000Z","link":"/题解集/LeetCode-167-两数之和-II-输入有序数组/"},{"title":"LeetCode 204. 计数质数","date":"2018-05-17T07:52:19.000Z","link":"/题解集/LeetCode-204-计数质数/"},{"title":"LeetCode 21. 合并两个有序链表","date":"2018-05-17T07:57:02.000Z","link":"/题解集/LeetCode-21-合并两个有序链表/"},{"title":"LeetCode 26. 删除排序数组中的重复项","date":"2018-05-17T08:05:52.000Z","link":"/题解集/LeetCode-26-删除排序数组中的重复项/"},{"title":"LeetCode 27. 移除元素","date":"2018-05-17T08:11:15.000Z","link":"/题解集/LeetCode-27-移除元素/"},{"title":"LeetCode 35. 搜索插入位置","date":"2018-05-17T08:14:52.000Z","link":"/题解集/LeetCode-35-搜索插入位置/"},{"title":"LeetCode 53. 最大子序和","date":"2018-05-17T09:29:01.000Z","link":"/题解集/LeetCode-53-最大子序和/"},{"title":"LeetCode 58. 最后一个单词的长度","date":"2018-05-18T04:02:15.000Z","link":"/题解集/LeetCode-58-最后一个单词的长度/"},{"title":"LeetCode 69. x 的平方根","date":"2018-05-18T04:07:02.000Z","link":"/题解集/LeetCode-69-x-的平方根/"},{"title":"LeetCode 7. 反转整数","date":"2018-05-18T04:10:35.000Z","link":"/题解集/LeetCode-7-反转整数/"},{"title":"LeetCode 83. 删除排序链表中的重复元素","date":"2018-05-18T04:18:37.000Z","link":"/题解集/LeetCode-83-删除排序链表中的重复元素/"},{"title":"LeetCode 88. 合并两个有序数组","date":"2018-05-18T04:22:41.000Z","link":"/题解集/LeetCode-88-合并两个有序数组/"},{"title":"余光中的诗","date":"2018-05-20T04:46:22.000Z","link":"/阅读/余光中的诗/"},{"title":"LeetCode118. 杨辉三角","date":"2018-05-20T05:32:42.000Z","link":"/题解集/LeetCode118-杨辉三角/"},{"title":"LeetCode100. 相同的树","date":"2018-05-20T05:38:23.000Z","link":"/题解集/LeetCode100-相同的树/"},{"title":"LeetCode104. 二叉树的最大深度","date":"2018-05-20T05:40:30.000Z","link":"/题解集/LeetCode104-二叉树的最大深度/"},{"title":"LeetCode121. 买卖股票的最佳时机","date":"2018-05-20T05:42:45.000Z","link":"/题解集/LeetCode121-买卖股票的最佳时机/"},{"title":"LeetCode191. 位1的个数","date":"2018-05-20T05:46:58.000Z","link":"/题解集/LeetCode191-位1的个数/"},{"title":"树状数组","date":"2018-05-21T05:59:31.000Z","link":"/算法和数据结构/树状数组/"},{"title":"172. 阶乘后的零","date":"2018-05-21T06:28:22.000Z","link":"/题解集/172-阶乘后的零/"},{"title":"28. 实现strStr()","date":"2018-05-21T07:13:30.000Z","link":"/题解集/28-实现strStr/"},{"title":"203. 删除链表中的节点","date":"2018-05-22T07:04:58.000Z","link":"/题解集/203-删除链表中的节点/"},{"title":"202. 快乐数","date":"2018-05-22T07:33:24.000Z","link":"/题解集/202-快乐数/"},{"title":"14. 最长公共前缀","date":"2018-05-22T09:11:55.000Z","link":"/题解集/14-最长公共前缀/"},{"title":"189. 旋转数组","date":"2018-05-23T05:38:56.000Z","link":"/题解集/189-旋转数组/"},{"title":"119. 杨辉三角 II","date":"2018-05-24T07:42:50.000Z","link":"/题解集/119-杨辉三角-II/"},{"title":"111. 二叉树的最小深度","date":"2018-05-24T07:58:46.000Z","link":"/题解集/111-二叉树的最小深度/"},{"title":"13. 罗马数字转整数","date":"2018-05-24T08:23:31.000Z","link":"/题解集/13-罗马数字转整数/"},{"title":"125. 验证回文串","date":"2018-05-25T07:47:57.000Z","link":"/题解集/125-验证回文串/"},{"title":"205. 同构字符串","date":"2018-05-25T08:23:06.000Z","link":"/题解集/205-同构字符串/"},{"title":"67. 二进制求和","date":"2018-05-26T05:00:51.000Z","link":"/题解集/67-二进制求和/"},{"title":"198. 打家劫舍","date":"2018-05-26T05:12:23.000Z","link":"/题解集/198-打家劫舍/"},{"title":"101. 对称二叉树","date":"2018-05-26T05:29:08.000Z","link":"/题解集/101-对称二叉树/"},{"title":"108. 将有序数组转换为二叉搜索树","date":"2018-05-26T05:59:19.000Z","link":"/题解集/108-将有序数组转换为二叉搜索树/"},{"title":"217. 存在重复元素","date":"2018-05-27T06:47:57.000Z","link":"/题解集/217-存在重复元素/"},{"title":"231. 2的幂","date":"2018-05-27T06:56:43.000Z","link":"/题解集/231-2的幂/"},{"title":"268. 缺失数字","date":"2018-05-27T07:09:05.000Z","link":"/题解集/268-缺失数字/"},{"title":"344. 反转字符串","date":"2018-05-27T07:18:21.000Z","link":"/题解集/344-反转字符串/"},{"title":"292. Nim游戏","date":"2018-05-27T07:24:54.000Z","link":"/题解集/292-Nim游戏/"},{"title":"258. 各位相加","date":"2018-05-27T07:32:34.000Z","link":"/题解集/258-各位相加/"},{"title":"110. 平衡二叉树","date":"2018-05-28T09:06:25.000Z","link":"/题解集/110-平衡二叉树/"},{"title":"L2-006 树的遍历（25 分）","date":"2018-05-29T07:25:23.000Z","link":"/题解集/L2-006-树的遍历（25-分）/"},{"title":"107. 二叉树的层次遍历 II","date":"2018-05-29T07:56:29.000Z","link":"/题解集/107-二叉树的层次遍历-II/"},{"title":"红黑树简介","date":"2018-05-29T08:27:17.000Z","link":"/算法和数据结构/红黑树简介/"},{"title":"卖米","date":"2018-05-30T00:16:57.000Z","link":"/阅读/卖米/"},{"title":"112. 路径总和","date":"2018-05-30T03:21:34.000Z","link":"/题解集/112-路径总和/"},{"title":"141. 环形链表","date":"2018-05-30T03:34:57.000Z","link":"/题解集/141-环形链表/"},{"title":"160. 相交链表","date":"2018-05-31T06:45:33.000Z","link":"/题解集/160-相交链表/"},{"title":"190. 颠倒二进制位","date":"2018-05-31T07:12:06.000Z","link":"/题解集/190-颠倒二进制位/"}],"2018-6":[{"title":"206. 反转链表","date":"2018-06-01T02:56:29.000Z","link":"/题解集/206-反转链表/"},{"title":"1025 反转链表 (25)（25 分）","date":"2018-06-02T06:37:28.000Z","link":"/题解集/1025-反转链表-25-（25-分）/"},{"title":"225. 用队列实现栈","date":"2018-06-02T07:13:01.000Z","link":"/题解集/225-用队列实现栈/"},{"title":"232. 用栈实现队列","date":"2018-06-02T07:32:50.000Z","link":"/题解集/232-用栈实现队列/"},{"title":"1030 完美数列(25)（25 分）","date":"2018-06-03T02:50:09.000Z","link":"/题解集/1030-完美数列-25-（25-分）/"},{"title":"226. 翻转二叉树","date":"2018-06-03T03:31:52.000Z","link":"/题解集/226-翻转二叉树/"},{"title":"219. 存在重复元素 II","date":"2018-06-03T07:11:39.000Z","link":"/题解集/219-存在重复元素-II/"},{"title":"237. 删除链表中的节点","date":"2018-06-03T07:22:09.000Z","link":"/题解集/237-删除链表中的节点/"},{"title":"263. 丑数","date":"2018-06-03T07:27:55.000Z","link":"/题解集/263-丑数/"},{"title":"看不见的客人","date":"2018-06-04T08:59:45.000Z","link":"/影音/看不见的客人/"},{"title":"1034 有理数四则运算(20)（20 分）","date":"2018-06-04T12:14:38.000Z","link":"/题解集/1034-有理数四则运算-20-（20-分）/"},{"title":"1035 插入与归并(25)（25 分）","date":"2018-06-04T12:15:50.000Z","link":"/题解集/1035-插入与归并-25-（25-分）/"},{"title":"383. 赎金信","date":"2018-06-04T12:54:36.000Z","link":"/题解集/383-赎金信/"},{"title":"L2-011 玩转二叉树（25 分）","date":"2018-06-05T07:31:15.000Z","link":"/题解集/L2-011-玩转二叉树（25-分）/"},{"title":"461. 汉明距离","date":"2018-06-05T07:41:48.000Z","link":"/题解集/461-汉明距离/"},{"title":"283. 移动零","date":"2018-06-05T08:04:33.000Z","link":"/题解集/283-移动零/"},{"title":"242. 有效的字母异位词","date":"2018-06-05T08:18:30.000Z","link":"/题解集/242-有效的字母异位词/"},{"title":"1045 快速排序(25)（25 分）","date":"2018-06-06T06:36:51.000Z","link":"/题解集/1045-快速排序-25-（25-分）/"},{"title":"257. Binary Tree Paths","date":"2018-06-08T05:07:30.000Z","link":"/题解集/257-Binary-Tree-Paths/"},{"title":"234. Palindrome Linked List","date":"2018-06-08T08:44:58.000Z","link":"/题解集/234-Palindrome-Linked-List/"},{"title":"235. Lowest Common Ancestor of a Binary Search Tree","date":"2018-06-09T04:34:37.000Z","link":"/题解集/235-Lowest-Common-Ancestor-of-a-Binary-Search-Tree/"},{"title":"326. 3的幂","date":"2018-06-09T08:48:46.000Z","link":"/题解集/326-3的幂/"},{"title":"342. 4的幂","date":"2018-06-09T08:55:38.000Z","link":"/题解集/342-4的幂/"},{"title":"367. 有效的完全平方数","date":"2018-06-10T13:13:05.000Z","link":"/题解集/367-有效的完全平方数/"},{"title":"349. 两个数组的交集","date":"2018-06-10T13:23:30.000Z","link":"/题解集/349-两个数组的交集/"},{"title":"350. 两个数组的交集 II","date":"2018-06-10T13:30:31.000Z","link":"/题解集/350-两个数组的交集-II/"},{"title":"345. 反转字符串中的元音字母","date":"2018-06-11T06:11:13.000Z","link":"/题解集/345-反转字符串中的元音字母/"},{"title":"371. 两整数之和","date":"2018-06-11T07:52:19.000Z","link":"/题解集/371-两整数之和/"},{"title":"374. 猜数字大小","date":"2018-06-14T06:08:11.000Z","link":"/题解集/374-猜数字大小/"},{"title":"389. 找不同","date":"2018-06-14T06:15:14.000Z","link":"/题解集/389-找不同/"},{"title":"414. 第三大的数","date":"2018-06-14T11:30:53.000Z","link":"/题解集/414-第三大的数/"},{"title":"《无题》北岛","date":"2018-06-17T07:55:29.000Z","link":"/阅读/《无题》北岛/"},{"title":"278. 第一个错误的版本","date":"2018-06-17T09:26:13.000Z","link":"/题解集/278-第一个错误的版本/"},{"title":"290. 单词模式","date":"2018-06-17T09:40:10.000Z","link":"/题解集/290-单词模式/"},{"title":"303. 区域和检索 - 数组不可变","date":"2018-06-17T11:25:29.000Z","link":"/题解集/303-区域和检索-数组不可变/"},{"title":"387. 字符串中的第一个唯一字符","date":"2018-06-17T12:54:03.000Z","link":"/题解集/387-字符串中的第一个唯一字符/"},{"title":"404. 左叶子之和","date":"2018-06-18T05:27:43.000Z","link":"/题解集/404-左叶子之和/"},{"title":"405. 数字转换为十六进制数","date":"2018-06-18T07:10:38.000Z","link":"/题解集/405-数字转换为十六进制数/"},{"title":"400. 第N个数字","date":"2018-06-18T07:27:24.000Z","link":"/题解集/400-第N个数字/"},{"title":"415. 字符串相加","date":"2018-06-19T13:45:07.000Z","link":"/题解集/415-字符串相加/"},{"title":"434. 字符串中的单词数","date":"2018-06-19T13:52:46.000Z","link":"/题解集/434-字符串中的单词数/"},{"title":"448. 找到所有数组中消失的数字","date":"2018-06-20T03:09:06.000Z","link":"/题解集/448-找到所有数组中消失的数字/"},{"title":"485. 最大连续1的个数","date":"2018-06-20T03:29:02.000Z","link":"/题解集/485-最大连续1的个数/"},{"title":"551. 学生出勤纪录 I","date":"2018-06-20T03:53:06.000Z","link":"/题解集/551-学生出勤纪录-I/"},{"title":"557. 反转字符串中的单词 III","date":"2018-06-20T03:58:54.000Z","link":"/题解集/557-反转字符串中的单词-III/"},{"title":"《追随》","date":"2018-06-20T10:03:12.000Z","link":"/影音/《追随》/"},{"title":"575. 分糖果","date":"2018-06-21T04:54:27.000Z","link":"/题解集/575-分糖果/"},{"title":"628. 三个数的最大乘积","date":"2018-06-21T05:24:21.000Z","link":"/题解集/628-三个数的最大乘积/"},{"title":"633. 平方数之和","date":"2018-06-21T05:37:22.000Z","link":"/题解集/633-平方数之和/"},{"title":"657. 判断路线成圈","date":"2018-06-21T05:43:55.000Z","link":"/题解集/657-判断路线成圈/"},{"title":"L2-021 点赞狂魔（25 分）","date":"2018-06-22T03:53:12.000Z","link":"/题解集/L2-021-点赞狂魔（25-分）/"},{"title":"852. 山脉数组的峰顶索引","date":"2018-06-22T04:10:45.000Z","link":"/题解集/852-山脉数组的峰顶索引/"},{"title":"728. 自除数","date":"2018-06-22T04:23:12.000Z","link":"/题解集/728-自除数/"},{"title":"771. 宝石与石头","date":"2018-06-22T04:35:56.000Z","link":"/题解集/771-宝石与石头/"},{"title":"L2-014 列车调度（25 分）","date":"2018-06-23T03:08:10.000Z","link":"/题解集/L2-014-列车调度（25-分）/"},{"title":"L2-013 红色警报（25 分）","date":"2018-06-23T04:06:52.000Z","link":"/题解集/L2-013-红色警报（25-分）/"},{"title":"453. 最小移动次数使数组元素相等","date":"2018-06-23T04:23:02.000Z","link":"/题解集/453-最小移动次数使数组元素相等/"},{"title":"455. 分发饼干","date":"2018-06-23T04:34:21.000Z","link":"/题解集/455-分发饼干/"},{"title":"532. 数组中的K-diff数对","date":"2018-06-27T12:34:28.000Z","link":"/题解集/532-数组中的K-diff数对/"},{"title":"561. 数组拆分 I","date":"2018-06-27T12:49:09.000Z","link":"/题解集/561-数组拆分-I/"},{"title":"747. 至少是其他数字两倍的最大数","date":"2018-06-27T13:09:43.000Z","link":"/题解集/747-至少是其他数字两倍的最大数/"}],"2018-7":[{"title":"744. 寻找比目标字母大的最小字母","date":"2018-07-04T10:24:48.000Z","link":"/题解集/744-寻找比目标字母大的最小字母/"},{"title":"441. 排列硬币","date":"2018-07-04T11:10:51.000Z","link":"/题解集/441-排列硬币/"},{"title":"860. 柠檬水找零","date":"2018-07-04T11:33:06.000Z","link":"/题解集/860-柠檬水找零/"},{"title":"80. 删除排序数组中的重复项 II","date":"2018-07-06T07:30:40.000Z","link":"/题解集/80-删除排序数组中的重复项-II/"},{"title":"红顶商人胡雪岩","date":"2018-07-06T10:51:46.000Z","link":"/阅读/红顶商人胡雪岩/"},{"title":"153. 寻找旋转排序数组中的最小值","date":"2018-07-06T12:06:50.000Z","link":"/题解集/153-寻找旋转排序数组中的最小值/"},{"title":"L2-012 关于堆的判断（25 分）","date":"2018-07-07T06:48:41.000Z","link":"/题解集/L2-012-关于堆的判断（25-分）/"},{"title":"L2-020 功夫传人（25 分）","date":"2018-07-07T07:10:31.000Z","link":"/题解集/L2-020-功夫传人（25-分）/"},{"title":"746. 使用最小花费爬楼梯","date":"2018-07-07T07:48:08.000Z","link":"/题解集/746-使用最小花费爬楼梯/"},{"title":"766. 托普利茨矩阵","date":"2018-07-07T07:59:32.000Z","link":"/题解集/766-托普利茨矩阵/"},{"title":"94. 二叉树的中序遍历","date":"2018-07-08T04:09:28.000Z","link":"/题解集/94-二叉树的中序遍历/"},{"title":"144. 二叉树的前序遍历","date":"2018-07-08T04:23:22.000Z","link":"/题解集/144-二叉树的前序遍历/"},{"title":"145. 二叉树的后序遍历","date":"2018-07-08T05:58:23.000Z","link":"/题解集/145-二叉树的后序遍历/"},{"title":"113. 路径总和 II","date":"2018-07-08T06:38:27.000Z","link":"/题解集/113-路径总和-II/"},{"title":"129. 求根到叶子节点数字之和","date":"2018-07-08T06:49:17.000Z","link":"/题解集/129-求根到叶子节点数字之和/"},{"title":"319. 灯泡开关","date":"2018-07-08T07:05:18.000Z","link":"/题解集/319-灯泡开关/"},{"title":"443. 压缩字符串","date":"2018-07-09T03:33:20.000Z","link":"/题解集/443-压缩字符串/"},{"title":"459. 重复的子字符串","date":"2018-07-09T06:39:06.000Z","link":"/题解集/459-重复的子字符串/"},{"title":"409. 最长回文串","date":"2018-07-09T06:57:52.000Z","link":"/题解集/409-最长回文串/"},{"title":"507. 完美数","date":"2018-07-09T07:20:56.000Z","link":"/题解集/507-完美数/"},{"title":"643. 子数组最大平均数 I","date":"2018-07-09T07:57:07.000Z","link":"/题解集/643-子数组最大平均数-I/"},{"title":"645. 错误的集合","date":"2018-07-09T08:20:37.000Z","link":"/题解集/645-错误的集合/"},{"title":"476. 数字的补数","date":"2018-07-10T02:23:04.000Z","link":"/题解集/476-数字的补数/"},{"title":"492. 构造矩形","date":"2018-07-10T02:37:51.000Z","link":"/题解集/492-构造矩形/"},{"title":"496. 下一个更大元素 I","date":"2018-07-10T03:26:41.000Z","link":"/题解集/496-下一个更大元素-I/"},{"title":"500. 键盘行","date":"2018-07-10T08:28:28.000Z","link":"/题解集/500-键盘行/"},{"title":"504. 七进制数","date":"2018-07-10T08:40:14.000Z","link":"/题解集/504-七进制数/"},{"title":"868. 转置矩阵","date":"2018-07-10T09:33:31.000Z","link":"/题解集/868-转置矩阵/"},{"title":"31. 下一个排列","date":"2018-07-11T08:24:54.000Z","link":"/题解集/31-下一个排列/"},{"title":"46. 全排列","date":"2018-07-11T08:39:51.000Z","link":"/题解集/46-全排列/"},{"title":"617. 合并二叉树","date":"2018-07-11T09:22:50.000Z","link":"/题解集/617-合并二叉树/"},{"title":"693. 交替位二进制数","date":"2018-07-12T07:26:05.000Z","link":"/题解集/693-交替位二进制数/"},{"title":"812. 最大三角形面积","date":"2018-07-12T08:05:31.000Z","link":"/题解集/812-最大三角形面积/"},{"title":"637. 二叉树的层平均值","date":"2018-07-12T08:42:16.000Z","link":"/题解集/637-二叉树的层平均值/"},{"title":"566. 重塑矩阵","date":"2018-07-13T07:10:30.000Z","link":"/题解集/566-重塑矩阵/"},{"title":"717. 1比特与2比特字符","date":"2018-07-13T07:42:28.000Z","link":"/题解集/717-1比特与2比特字符/"},{"title":"401. 二进制手表","date":"2018-07-13T07:51:39.000Z","link":"/题解集/401-二进制手表/"},{"title":"844. 比较含退格的字符串","date":"2018-07-13T08:24:36.000Z","link":"/题解集/844-比较含退格的字符串/"},{"title":"605. 种花问题","date":"2018-07-13T08:44:34.000Z","link":"/题解集/605-种花问题/"},{"title":"682. 棒球比赛","date":"2018-07-13T09:18:04.000Z","link":"/题解集/682-棒球比赛/"},{"title":"L2-024 部落（25 分）","date":"2018-07-19T03:45:34.000Z","link":"/题解集/L2-024-部落（25-分）/"},{"title":"L2-023 图着色问题（25 分）","date":"2018-07-19T04:05:04.000Z","link":"/题解集/L2-023-图着色问题（25-分）/"},{"title":"804. 唯一摩尔斯密码词","date":"2018-07-19T09:24:09.000Z","link":"/题解集/804-唯一摩尔斯密码词/"},{"title":"653. 两数之和 IV - 输入 BST","date":"2018-07-19T09:49:39.000Z","link":"/题解集/653-两数之和-IV-输入-BST/"},{"title":"709. 转换成小写字母","date":"2018-07-19T10:18:26.000Z","link":"/题解集/709-转换成小写字母/"},{"title":"572. 另一个树的子树","date":"2018-07-19T10:34:30.000Z","link":"/题解集/572-另一个树的子树/"},{"title":"868. 二进制间距","date":"2018-07-20T14:26:09.000Z","link":"/题解集/868-二进制间距/"},{"title":"704. Binary Search","date":"2018-07-20T14:42:57.000Z","link":"/题解集/704-Binary-Search/"},{"title":"696. 计数二进制子串","date":"2018-07-20T14:56:28.000Z","link":"/题解集/696-计数二进制子串/"},{"title":"832. 翻转图像","date":"2018-07-20T15:17:23.000Z","link":"/题解集/832-翻转图像/"},{"title":"74. 搜索二维矩阵","date":"2018-07-20T15:45:06.000Z","link":"/题解集/74-搜索二维矩阵/"},{"title":"437. 路径总和 III","date":"2018-07-22T09:27:39.000Z","link":"/题解集/437-路径总和-III/"},{"title":"447. 回旋镖的数量","date":"2018-07-22T09:49:37.000Z","link":"/题解集/447-回旋镖的数量/"},{"title":"438. 找到字符串中所有字母异位词","date":"2018-07-22T10:07:40.000Z","link":"/题解集/438-找到字符串中所有字母异位词/"},{"title":"458. 可怜的小猪","date":"2018-07-22T10:16:29.000Z","link":"/题解集/458-可怜的小猪/"},{"title":"463. 岛屿的周长","date":"2018-07-26T12:02:10.000Z","link":"/题解集/463-岛屿的周长/"},{"title":"506. 相对名次","date":"2018-07-26T12:43:10.000Z","link":"/题解集/506-相对名次/"},{"title":"521. 最长特殊序列 Ⅰ","date":"2018-07-26T12:57:58.000Z","link":"/题解集/521-最长特殊序列-Ⅰ/"},{"title":"530. 二叉搜索树的最小绝对差","date":"2018-07-26T13:26:44.000Z","link":"/题解集/530-二叉搜索树的最小绝对差/"},{"title":"538. 把二叉搜索树转换为累加树","date":"2018-07-26T13:38:37.000Z","link":"/题解集/538-把二叉搜索树转换为累加树/"},{"title":"541. 反转字符串 II","date":"2018-07-26T14:04:15.000Z","link":"/题解集/541-反转字符串-II/"},{"title":"872. 叶子相似的树","date":"2018-07-26T14:17:16.000Z","link":"/题解集/872-叶子相似的树/"},{"title":"641. Design Circular Deque","date":"2018-07-28T14:35:31.000Z","link":"/题解集/641-Design-Circular-Deque/"},{"title":"543. 二叉树的直径","date":"2018-07-28T14:50:31.000Z","link":"/题解集/543-二叉树的直径/"},{"title":"1067 Sort with Swap(0,*) (25)（25 分）","date":"2018-07-29T08:09:02.000Z","link":"/题解集/1067-Sort-with-Swap-0-25-（25-分）/"},{"title":"1096 Consecutive Factors (20)（20 分）","date":"2018-07-31T07:29:51.000Z","link":"/题解集/1096-Consecutive-Factors-20-（20-分）/"},{"title":"606. 根据二叉树创建字符串","date":"2018-07-31T14:29:07.000Z","link":"/题解集/606-根据二叉树创建字符串/"},{"title":"563. 二叉树的坡度","date":"2018-07-31T14:52:11.000Z","link":"/题解集/563-二叉树的坡度/"},{"title":"501. 二叉搜索树中的众数","date":"2018-07-31T15:13:17.000Z","link":"/题解集/501-二叉搜索树中的众数/"}],"2018-8":[{"title":"876. 链表的中间结点","date":"2018-08-01T07:04:24.000Z","link":"/题解集/876-链表的中间结点/"},{"title":"581. 最短无序连续子数组","date":"2018-08-01T08:36:35.000Z","link":"/题解集/581-最短无序连续子数组/"},{"title":"598. 范围求和 II","date":"2018-08-01T09:34:27.000Z","link":"/题解集/598-范围求和-II/"},{"title":"599. 两个列表的最小索引总和","date":"2018-08-01T09:49:22.000Z","link":"/题解集/599-两个列表的最小索引总和/"},{"title":"482. 密钥格式化","date":"2018-08-02T14:57:47.000Z","link":"/题解集/482-密钥格式化/"},{"title":"475. 供暖器","date":"2018-08-02T15:07:41.000Z","link":"/题解集/475-供暖器/"},{"title":"479. 最大回文数乘积","date":"2018-08-03T14:47:53.000Z","link":"/题解集/479-最大回文数乘积/"},{"title":"669. 修剪二叉搜索树","date":"2018-08-10T13:50:12.000Z","link":"/题解集/669-修剪二叉搜索树/"},{"title":"671. 二叉树中第二小的节点","date":"2018-08-10T14:15:21.000Z","link":"/题解集/671-二叉树中第二小的节点/"},{"title":"783. 二叉搜索树结点最小距离","date":"2018-08-10T14:41:27.000Z","link":"/题解集/783-二叉搜索树结点最小距离/"},{"title":"700. 二叉搜索树中的搜索","date":"2018-08-11T04:07:53.000Z","link":"/题解集/700-二叉搜索树中的搜索/"},{"title":"724. 寻找数组的中心索引","date":"2018-08-11T04:21:53.000Z","link":"/题解集/724-寻找数组的中心索引/"},{"title":"821. 字符的最短距离","date":"2018-08-11T06:43:46.000Z","link":"/题解集/821-字符的最短距离/"},{"title":"849. 到最近的人的最大距离","date":"2018-08-11T12:44:52.000Z","link":"/题解集/849-到最近的人的最大距离/"},{"title":"695. 岛屿的最大面积","date":"2018-08-11T14:48:56.000Z","link":"/题解集/695-岛屿的最大面积/"},{"title":"836. 矩形重叠","date":"2018-08-12T05:10:18.000Z","link":"/题解集/836-矩形重叠/"},{"title":"661. 图片平滑器","date":"2018-08-12T09:45:14.000Z","link":"/题解集/661-图片平滑器/"},{"title":"674. 最长连续递增序列","date":"2018-08-12T09:53:05.000Z","link":"/题解集/674-最长连续递增序列/"},{"title":"680. 验证回文字符串 Ⅱ","date":"2018-08-12T14:48:02.000Z","link":"/题解集/680-验证回文字符串-Ⅱ/"},{"title":"705. 设计哈希集合","date":"2018-08-13T16:24:27.000Z","link":"/题解集/705-设计哈希集合/"},{"title":"706. 设计哈希映射","date":"2018-08-13T16:35:05.000Z","link":"/题解集/706-设计哈希映射/"},{"title":"830. 较大分组的位置","date":"2018-08-18T11:43:19.000Z","link":"/题解集/830-较大分组的位置/"},{"title":"665. 非递减数列","date":"2018-08-21T07:12:44.000Z","link":"/题解集/665-非递减数列/"},{"title":"690. 员工的重要性","date":"2018-08-21T07:44:48.000Z","link":"/题解集/690-员工的重要性/"},{"title":"686. 重复叠加字符串匹配","date":"2018-08-21T07:57:59.000Z","link":"/题解集/686-重复叠加字符串匹配/"},{"title":"687. 最长同值路径","date":"2018-08-21T08:09:56.000Z","link":"/题解集/687-最长同值路径/"},{"title":"707. 设计链表","date":"2018-08-21T09:02:09.000Z","link":"/题解集/707-设计链表/"}],"2018-9":[{"title":"15. 三数之和","date":"2018-09-06T05:45:08.000Z","link":"/题解集/15-三数之和/"},{"title":"16. 最接近的三数之和","date":"2018-09-06T07:53:18.000Z","link":"/题解集/16-最接近的三数之和/"},{"title":"154. 寻找旋转排序数组中的最小值 II","date":"2018-09-08T07:35:45.000Z","link":"/题解集/154-寻找旋转排序数组中的最小值-II/"},{"title":"2018上半年的阅读整理","date":"2018-09-20T02:52:28.000Z","link":"/阅读/2018上半年的阅读整理/"},{"title":"Git 与Ｇithub入门介绍","date":"2018-09-27T14:22:17.000Z","link":"/业务开发/Git-入门介绍/"}],"2018-10":[{"title":"JavaWeb开发环境设置","date":"2018-10-01T05:39:58.000Z","link":"/业务开发/JavaWeb开发环境设置/"},{"title":"4. 两个排序数组的中位数","date":"2018-10-01T12:25:52.000Z","link":"/题解集/4-两个排序数组的中位数/"},{"title":"128. 最长连续序列","date":"2018-10-01T12:40:57.000Z","link":"/题解集/128-最长连续序列/"},{"title":"来普陀山拜观音了","date":"2018-10-04T10:48:41.000Z","link":"/随笔/来普陀山拜观音了/"},{"title":"如何在Windows和Mac平台上协同管理hexo博客","date":"2018-10-10T09:12:56.000Z","link":"/业务开发/如何在Windows和Mac平台上协同管理hexo博客/"},{"title":"19. 删除链表的倒数第N个节点","date":"2018-10-14T14:06:13.000Z","link":"/题解集/19-删除链表的倒数第N个节点/"},{"title":"谈谈一部争议较大的日漫《缘之空》","date":"2018-10-16T08:33:45.000Z","link":"/影音/谈谈一部争议较大的日漫《缘之空》/"},{"title":"137. 只出现一次的数字 II","date":"2018-10-17T13:16:44.000Z","link":"/题解集/137-只出现一次的数字-II/"},{"title":"支持推理小说家紫金陈","date":"2018-10-19T06:29:55.000Z","link":"/阅读/支持推理小说家紫金陈/"},{"title":"24. 两两交换链表中的节点","date":"2018-10-19T13:12:06.000Z","link":"/题解集/24-两两交换链表中的节点/"},{"title":"Java容器概述","date":"2018-10-22T08:39:48.000Z","link":"/语言/Java容器概述/"},{"title":"11. 盛最多水的容器","date":"2018-10-25T07:27:41.000Z","link":"/题解集/11-盛最多水的容器/"},{"title":"回顾自己部署hexo博客的血泪史","date":"2018-10-29T14:52:02.000Z","link":"/随笔/回顾自己部署hexo博客的血泪史/"}],"2018-11":[{"title":"普通人如何稳固对自我价值的认同感","date":"2018-11-07T06:01:18.000Z","link":"/随笔/普通人如何稳固对自我价值的认同感/"},{"title":"如何为Nginx服务器配置ssl证书","date":"2018-11-21T13:14:42.000Z","link":"/业务开发/如何为Nginx服务器配置ssl证书/"}],"2018-12":[{"title":"为什么我说考验人性多半会令你失望","date":"2018-12-25T07:42:51.000Z","link":"/随笔/为什么我说考验人性多半会令你失望/"}],"2019-3":[{"title":"风口过了，猪还是猪","date":"2019-03-02T04:08:27.000Z","link":"/随笔/风口过了，猪还是猪/"},{"title":"一个成功的git分支模型","date":"2019-03-16T11:20:45.000Z","link":"/译文集/一个成功的git分支模型/"}],"2019-4":[{"title":"蘑菇街Java实习凉面","date":"2019-04-16T13:55:11.000Z","link":"/业务开发/蘑菇街Java实习凉面/"},{"title":"redis数据结构入门","date":"2019-04-27T12:35:16.000Z","link":"/业务开发/redis数据结构入门/"}],"2019-6":[{"title":"ArrayList源码阅读","date":"2019-06-23T06:04:41.000Z","link":"/算法和数据结构/ArrayList源码阅读/"}],"2019-7":[{"title":"字节跳动提前批第二批笔试题","date":"2019-07-16T05:11:27.000Z","link":"/题解集/字节跳动提前批第二批笔试题/"}],"2019-8":[{"title":"腾讯LeetCode50题 155. 最小栈","date":"2019-08-03T11:23:39.000Z","link":"/题解集/155-最小栈/"},{"title":"腾讯LeetCode50题 20. 有效的括号","date":"2019-08-03T11:51:29.000Z","link":"/题解集/20-有效的括号/"},{"title":"腾讯LeetCode50题 215数组中的第K个最大元素","date":"2019-08-04T12:48:29.000Z","link":"/题解集/215数组中的第K个最大元素/"},{"title":"腾讯精选50题 122. 买卖股票的最佳时机 II","date":"2019-08-06T08:10:07.000Z","link":"/题解集/122-买卖股票的最佳时机-II/"},{"title":"23. 合并K个排序链表","date":"2019-08-06T12:39:53.000Z","link":"/题解集/23-合并K个排序链表/"}]}